{
  "region": "US",
  "generated_at": "2026-07-22T12:11:18.013Z",
  "counts": {
    "total": 1,
    "by_tier": {
      "1": 0,
      "2": 1
    },
    "by_source": {
      "Lightspeed": 1
    }
  },
  "items": [
    {
      "id": "lightspeed-cuspai-1784681509000",
      "title": "CuspAI",
      "source_name": "Lightspeed",
      "source_tier": 2,
      "source_url": "https://lsvp.com/company/cuspai/",
      "published_at": "2026-07-22T00:51:49.000Z",
      "raw_excerpt": "The post CuspAI appeared first on Lightspeed Venture Partners .",
      "region": "US",
      "topics": [
        "vc-thesis"
      ]
    }
  ]
}